mySQLDBCtrlAPI/__init__.py
mySQLDBCtrlAPI/mySQLDBCtrl.cp310-win_amd64.pyd
mySQLDBCtrlAPI/mySQLDBCtrl.pyi
mySQLDBCtrlAPI/mySQLNetSSH.cp310-win_amd64.pyd
mySQLDBCtrlAPI/mySQLNetSSH.pyi
mySQLDBCtrlAPI/mySQLxJsonLIB.cp310-win_amd64.pyd
mySQLDBCtrlAPI/mySQLxJsonLIB.pyi
mySQLDBCtrlAPI/out/mySQLDBCtrlAPI/mySQLDBCtrl.pyi
mySQLDBCtrlAPI/out/mySQLDBCtrlAPI/mySQLNetSSH.pyi
mySQLDBCtrlAPI/out/mySQLDBCtrlAPI/mySQLxJsonLIB.pyi
mysqldbctrlapi-1.2512.1201.dist-info/licenses/LICENSE
mysqldbctrlapi-1.2512.1201.dist-info/METADATA
mysqldbctrlapi-1.2512.1201.dist-info/WHEEL
mysqldbctrlapi-1.2512.1201.dist-info/top_level.txt
mysqldbctrlapi-1.2512.1201.dist-info/RECORD
