Metadata-Version: 2.4
Name: mySQLDBCtrlAPI
Version: 1.2512.1201
Summary: mySQLDBCtrlAPI Python package
Author-email: James Lin <tylin123@ms27.hinet.net>
License: Copyright (c) 2025 James Lin
Project-URL: Homepage, https://mis.gotech.biz
Requires-Python: >=3.10
License-File: LICENSE
Requires-Dist: pymysql
Requires-Dist: sshtunnel
Requires-Dist: ulid-py
Requires-Dist: paramiko
Dynamic: license-file
